MANIFEST.in
setup.py
ReportChangesRSSPlugin.egg-info/PKG-INFO
ReportChangesRSSPlugin.egg-info/SOURCES.txt
ReportChangesRSSPlugin.egg-info/dependency_links.txt
ReportChangesRSSPlugin.egg-info/entry_points.txt
ReportChangesRSSPlugin.egg-info/not-zip-safe
ReportChangesRSSPlugin.egg-info/top_level.txt
reportchangesrss/__init__.py
reportchangesrss/api.py
reportchangesrss/templates/changesrss.rss