Metadata-Version: 1.0
Name: ReportChangesRSSPlugin
Version: 0.1.2
Summary: Extends reports with RSS feed of ticket changes.
Home-page: http://mitar.tnode.com/
Author: Mitar
Author-email: mitar.trac@tnode.com
License: AGPLv3
Keywords: trac plugin
Platform: UNKNOWN
